art_of_geom/__init__.py
art_of_geom/_util/_compat.py
art_of_geom/_util/_debug.py
art_of_geom/_util/_inspect.py
art_of_geom/_util/_log.py
art_of_geom/_util/_tmp.py
art_of_geom/_util/_type.py
art_of_geom/art/__init__.py
art_of_geom/geom/__init__.py
art_of_geom/geom/_abc/_entity.py
art_of_geom/geom/_abc/_line.py
art_of_geom/geom/_abc/_point.py
art_of_geom/geom/_abc/_session.py
art_of_geom/geom/_abc/_space.py
art_of_geom/geom/euclid/_abc/_coord.py
art_of_geom/geom/euclid/_abc/_entity.py
art_of_geom/geom/euclid/_abc/_line.py
art_of_geom/geom/euclid/_abc/_point.py
art_of_geom/geom/euclid/_abc/_space.py
art_of_geom/geom/euclid/_r0/_point.py
art_of_geom/geom/euclid/_r1/_abc/_entity.py
art_of_geom/geom/euclid/_r1/_space.py
art_of_geom/geom/euclid/_r1/_sphere.py
art_of_geom/geom/euclid/_r1/coord.py
art_of_geom/geom/euclid/_r1/point.py
art_of_geom/geom/euclid/_rD/plane.py
art_of_geom/geom/euclid/_rD/point.py
art_of_geom/geom/euclid/_rD/sphere.py
art_of_geom/geom/euclid/_rDi/__init__.py
art_of_geom/geom/euclid/r2/_abc/_entity.py
art_of_geom/geom/euclid/r2/_space.py
art_of_geom/geom/euclid/r2/angle.py
art_of_geom/geom/euclid/r2/circle.py
art_of_geom/geom/euclid/r2/conic/__init__.py
art_of_geom/geom/euclid/r2/conic/ellipse.py
art_of_geom/geom/euclid/r2/conic/hyperbola.py
art_of_geom/geom/euclid/r2/conic/parabola.py
art_of_geom/geom/euclid/r2/coord.py
art_of_geom/geom/euclid/r2/cubic/__init__.py
art_of_geom/geom/euclid/r2/intersect/__init__.py
art_of_geom/geom/euclid/r2/line.py
art_of_geom/geom/euclid/r2/point.py
art_of_geom/geom/euclid/r2/polygon/__init__.py
art_of_geom/geom/euclid/r2/polygon/quadrilateral/__init__.py
art_of_geom/geom/euclid/r2/polygon/triangle/__init__.py
art_of_geom/geom/euclid/r2/polygon/triangle/center/__init__.py
art_of_geom/geom/euclid/r2/polygon/triangle/center/kimberling/__init__.py
art_of_geom/geom/euclid/r2/quartic/__init__.py
art_of_geom/geom/euclid/r2/roulette/__init__.py
art_of_geom/geom/euclid/r2/roulette/brachistochrone.py
art_of_geometry-0.0.0.dev0.dist-info/entry_points.txt
art_of_geometry-0.0.0.dev0.dist-info/LICENSE
art_of_geometry-0.0.0.dev0.dist-info/WHEEL
art_of_geometry-0.0.0.dev0.dist-info/METADATA
art_of_geometry-0.0.0.dev0.dist-info/RECORD
